mnj/__init__.py
mnj/exceptions.py
mnj/compat/__init__.py
mnj/compat/regex.py
mnj/document/__init__.py
mnj/document/base.py
mnj/document/document.py
mnj/document/exceptions.py
mnj/document/query.py
mnj/document/registry.py
mnj/document/types.py
mnj/operators/__init__.py
mnj/operators/base.py
mnj/operators/exceptions.py
mnj/operators/query/__init__.py
mnj/operators/query/array.py
mnj/operators/query/bitwise.py
mnj/operators/query/comparison.py
mnj/operators/query/element.py
mnj/operators/query/evaluation.py
mnj/operators/query/logical.py
mnj-0.3.0.dist-info/COPYING
mnj-0.3.0.dist-info/METADATA
mnj-0.3.0.dist-info/WHEEL
mnj-0.3.0.dist-info/top_level.txt
mnj-0.3.0.dist-info/RECORD
